TideServer-0.2a5.dist-info/LICENSE.txt
TideServer-0.2a5.dist-info/METADATA
TideServer-0.2a5.dist-info/RECORD
TideServer-0.2a5.dist-info/WHEEL
TideServer-0.2a5.dist-info/top_level.txt
tideserver/__init__.py
tideserver/tideserver.py
